MANIFEST.in
README.md
setup.py
Botic.egg-info/PKG-INFO
Botic.egg-info/SOURCES.txt
Botic.egg-info/dependency_links.txt
Botic.egg-info/entry_points.txt
Botic.egg-info/requires.txt
Botic.egg-info/top_level.txt
botic/__init__.py
botic/basebot.py
botic/botic.py
botic/cli.py
botic/defaults.py
botic/dumpdata.py
botic/hashml.py
botic/historicaldata.py
botic/top.py
botic/util.py
botic/data/historical-btc.csv.gz
botic/exchange/__init__.py
botic/exchange/backtest.py
botic/exchange/backtesthashml.py
botic/exchange/base.py
botic/exchange/coinbasepro.py
botic/exchange/exceptions.py
botic/trader/__init__.py
botic/trader/base.py
botic/trader/hashmltrader.py
botic/trader/hodlstoploss.py
botic/trader/meanreversion.py
botic/trader/simple.py
botic/trader/simpleslide.py
botic/trader/test1.py
botic/trader/test2.py
botic/trader/test3.py