Metadata-Version: 2.1
Name: Botic
Version: 1.1.4
Summary: UNKNOWN
Home-page: https://github.com/mtingers/botic
Author: Matth Ingersoll
Author-email: matth@mtingers.com
License: GPLv3
Platform: UNKNOWN
Classifier: Intended Audience :: Developers
Classifier: License :: OSI Approved :: GNU General Public License v3 or later (GPLv3+)
Classifier: Programming Language :: Python :: 3
Classifier: Programming Language :: Python :: 3.5
Classifier: Programming Language :: Python :: 3.6
Classifier: Programming Language :: Python :: 3.7
Classifier: Programming Language :: Python :: 3.8
Classifier: Programming Language :: Python :: 3.9
